mesph-1.0.data/scripts/main.py
mesph-1.0.data/scripts/measures_error.py
utils/__init__.py
utils/conversions.py
utils/hdf5_utils.py
utils/parameters.py
utils/physics.py
utils/sampling.py
utils/sph_utils.py
mesph-1.0.dist-info/LICENSE
mesph-1.0.dist-info/METADATA
mesph-1.0.dist-info/WHEEL
mesph-1.0.dist-info/top_level.txt
mesph-1.0.dist-info/RECORD
