Metadata-Version: 2.1
Name: mesph
Version: 1.0
Summary: This is a program that transforms a set of outputs simulation files from FARGO3D into a SPH data, specifically to a GADGET-3 file with HDF5 format.
Home-page: https://github.com/DennisUrr/mesph
Author: Dennis Urrutia
Author-email: dennis.urrutia@usach.cl
License: LICENSE
Keywords: sph,eulerian mesh,fargo3d,gadget-3,hdf5,transformation,extrapolation
License-File: LICENSE
Requires-Dist: numpy >=1.21.5
Requires-Dist: h5py >=3.8.0
Requires-Dist: scipy >=1.7.3
Requires-Dist: matplotlib >=3.5.3
